task3/dual_port_ram.sv
module dual_port_ram #(
    parameter AW = 9,  // Address width (512 locations = 9 bits)
    parameter DW = 8   // Data width (8 bits per sample)
)(
    input  logic             clk,
    input  logic [AW-1:0]    write_addr,
    input  logic [AW-1:0]    read_addr,
    input  logic [DW-1:0]    data_in,
    input  logic             write_en,
    output logic [DW-1:0]    data_out
);

// RAM array
logic [DW-1:0] ram [2**AW-1:0];

// Write port
always_ff @(posedge clk) begin
    if (write_en) begin
        ram[write_addr] <= data_in;
    end
end

// Read port (continuous read)
assign data_out = ram[read_addr];

endmodule

task3/counter.sv
module counter #(
    parameter WIDTH = 9  // 9 bits for 512 locations
)(
    input  logic             clk,
    input  logic             rst,
    input  logic             en,
    output logic [WIDTH-1:0] count
);

always_ff @(posedge clk) begin
    if (rst)
        count <= {WIDTH{1'b0}};
    else if (en)
        count <= count + 1'b1;
end

endmodule

task3/sigdelay.sv
module sigdelay #(
    parameter AW = 9,    // Address width
    parameter DW = 8     // Data width
)(
    input  logic             clk,
    input  logic             rst,
    input  logic             en,
    input  logic [DW-1:0]    mic_in,     // Microphone input
    input  logic [AW-1:0]    delay,      // Delay amount
    output logic [DW-1:0]    original,   // Original signal
    output logic [DW-1:0]    delayed     // Delayed signal
);

// Internal signals
logic [AW-1:0] write_addr;
logic [AW-1:0] read_addr;

// Counter for write address
counter #(AW) write_counter (
    .clk    (clk),
    .rst    (rst),
    .en     (en),
    .count  (write_addr)
);

// Calculate read address with delay
assign read_addr = write_addr - delay;

// Dual port RAM instance
dual_port_ram #(AW, DW) u_ram (
    .clk        (clk),
    .write_addr (write_addr),
    .read_addr  (read_addr),
    .data_in    (mic_in),
    .write_en   (en),
    .data_out   (delayed)
);

// Output the original signal directly
assign original = mic_in;

endmodule

task3/sigdelay.vcd
$version Generated by VerilatedVcd $end
$timescale 1ps $end
 $scope module TOP $end
  $var wire 1 # clk $end
  $var wire 1 $ rst $end
  $var wire 1 % en $end
  $var wire 8 & mic_in [7:0] $end
  $var wire 9 ' delay [8:0] $end
  $var wire 8 ( original [7:0] $end
  $var wire 8 ) delayed [7:0] $end
  $scope module sigdelay $end
   $var wire 32 , AW [31:0] $end
   $var wire 32 - DW [31:0] $end
   $var wire 1 # clk $end
   $var wire 1 $ rst $end
   $var wire 1 % en $end
   $var wire 8 & mic_in [7:0] $end
   $var wire 9 ' delay [8:0] $end
   $var wire 8 ( original [7:0] $end
   $var wire 8 ) delayed [7:0] $end
   $var wire 9 * write_addr [8:0] $end
   $var wire 9 + read_addr [8:0] $end
   $scope module u_ram $end
    $var wire 32 , AW [31:0] $end
    $var wire 32 - DW [31:0] $end
    $var wire 1 # clk $end
    $var wire 9 * write_addr [8:0] $end
    $var wire 9 + read_addr [8:0] $end
    $var wire 8 & data_in [7:0] $end
    $var wire 1 % write_en $end
    $var wire 8 ) data_out [7:0] $end
   $upscope $end
   $scope module write_counter $end
    $var wire 32 , WIDTH [31:0] $end
    $var wire 1 # clk $end
    $var wire 1 $ rst $end
    $var wire 1 % en $end
    $var wire 9 * count [8:0] $end
   $upscope $end
  $upscope $end
 $upscope $end
$enddefinitions $end


#0
1#
0$
1%
b00000000 &
b000000000 '
b00000000 (
b00000000 )
b000000000 *
b000000000 +
b00000000000000000000000000001001 ,
b00000000000000000000000000001000 -
#1
0#
#2
1#
b01100100 &
b000110011 '
b000000001 *
b111001110 +
#3
0#
b01100100 (
#4
1#
b01100101 &
b000000010 *
b111001111 +
#5
0#
b01100101 (
#6
1#
b01100011 &
b000000011 *
b111010000 +
#7
0#
b01100011 (
#8
1#
b01100010 &
b000000100 *
b111010001 +
#9
0#
b01100010 (
#10
1#
b01100000 &
b000000101 *
b111010010 +
#11
0#
b01100000 (
#12
1#
b01100101 &
b000000110 *
b111010011 +
#13
0#
b01100101 (
#14
1#
b01100100 &
b000000111 *
b111010100 +
#15
0#
b01100100 (
#16
1#
b01100001 &
b000001000 *
b111010101 +
#17
0#
b01100001 (
#18
1#
b01100101 &
b000001001 *
b111010110 +
#19
0#
b01100101 (
#20
1#
b01100110 &
b000001010 *
b111010111 +
#21
0#
b01100110 (
#22
1#
b01100100 &
b000001011 *
b111011000 +
#23
0#
b01100100 (
#24
1#
b01101000 &
b000001100 *
b111011001 +
#25
0#
b01101000 (
#26
1#
b01100100 &
b000001101 *
b111011010 +
#27
0#
b01100100 (
#28
1#
b01100110 &
b000001110 *
b111011011 +
#29
0#
b01100110 (
#30
1#
b01100101 &
b000001111 *
b111011100 +
#31
0#
b01100101 (
#32
1#
b01101000 &
b000010000 *
b111011101 +
#33
0#
b01101000 (
#34
1#
b000010001 *
b111011110 +
#35
0#
#36
1#
b01101010 &
b000010010 *
b111011111 +
#37
0#
b01101010 (
#38
1#
b01101000 &
b000010011 *
b111100000 +
#39
0#
b01101000 (
#40
1#
b01101010 &
b000010100 *
b111100001 +
#41
0#
b01101010 (
#42
1#
b01101011 &
b000010101 *
b111100010 +
#43
0#
b01101011 (
#44
1#
b01101100 &
b000010110 *
b111100011 +
#45
0#
b01101100 (
#46
1#
b000010111 *
b111100100 +
#47
0#
#48
1#
b01101101 &
b000011000 *
b111100101 +
#49
0#
b01101101 (
#50
1#
b01101111 &
b000011001 *
b111100110 +
#51
0#
b01101111 (
#52
1#
b01110011 &
b000011010 *
b111100111 +
#53
0#
b01110011 (
#54
1#
b01110101 &
b000011011 *
b111101000 +
#55
0#
b01110101 (
#56
1#
b000011100 *
b111101001 +
#57
0#
#58
1#
b01110100 &
b000011101 *
b111101010 +
#59
0#
b01110100 (
#60
1#
b01110110 &
b000011110 *
b111101011 +
#61
0#
b01110110 (
#62
1#
b000011111 *
b111101100 +
#63
0#
#64
1#
b01110101 &
b000100000 *
b111101101 +
#65
0#
b01110101 (
#66
1#
b01110011 &
b000100001 *
b111101110 +
#67
0#
b01110011 (
#68
1#
b01110101 &
b000100010 *
b111101111 +
#69
0#
b01110101 (
#70
1#
b01110010 &
b000100011 *
b111110000 +
#71
0#
b01110010 (
#72
1#
b01101111 &
b000100100 *
b111110001 +
#73
0#
b01101111 (
#74
1#
b000100101 *
b111110010 +
#75
0#
#76
1#
b01110000 &
b000100110 *
b111110011 +
#77
0#
b01110000 (
#78
1#
b01110001 &
b000100111 *
b111110100 +
#79
0#
b01110001 (
#80
1#
b01110000 &
b000101000 *
b111110101 +
#81
0#
b01110000 (
#82
1#
b01110110 &
b000101001 *
b111110110 +
#83
0#
b01110110 (
#84
1#
b01110001 &
b000101010 *
b111110111 +
#85
0#
b01110001 (
#86
1#
b01110101 &
b000101011 *
b111111000 +
#87
0#
b01110101 (
#88
1#
b01110100 &
b000101100 *
b111111001 +
#89
0#
b01110100 (
#90
1#
b01110110 &
b000101101 *
b111111010 +
#91
0#
b01110110 (
#92
1#
b01110100 &
b000101110 *
b111111011 +
#93
0#
b01110100 (
#94
1#
b01110101 &
b000101111 *
b111111100 +
#95
0#
b01110101 (
#96
1#
b01110001 &
b000110000 *
b111111101 +
#97
0#
b01110001 (
#98
1#
b000110001 *
b111111110 +
#99
0#
#100
1#
b01101111 &
b000110010 *
b111111111 +
#101
0#
b01101111 (
#102
1#
b000110011 *
b000000000 +
#103
0#
#104
1#
b01101100 &
b01100100 )
b000110100 *
b000000001 +
#105
0#
b01101100 (
#106
1#
b01101001 &
b01100101 )
b000110101 *
b000000010 +
#107
0#
b01101001 (
#108
1#
b01101011 &
b01100011 )
b000110110 *
b000000011 +
#109
0#
b01101011 (
#110
1#
b01100111 &
b01100010 )
b000110111 *
b000000100 +
#111
0#
b01100111 (
#112
1#
b01101001 &
b01100000 )
b000111000 *
b000000101 +
#113
0#
b01101001 (
#114
1#
b01101000 &
b01100101 )
b000111001 *
b000000110 +
#115
0#
b01101000 (
#116
1#
b01100101 &
b01100100 )
b000111010 *
b000000111 +
#117
0#
b01100101 (
#118
1#
b01100001 )
b000111011 *
b000001000 +
#119
0#
#120
1#
b01100111 &
b01100101 )
b000111100 *
b000001001 +
#121
0#
b01100111 (
#122
1#
b01101000 &
b01100110 )
b000111101 *
b000001010 +
#123
0#
b01101000 (
#124
1#
b01100100 )
b000111110 *
b000001011 +
#125
0#
#126
1#
b01100101 &
b01101000 )
b000111111 *
b000001100 +
#127
0#
b01100101 (
#128
1#
b01100100 )
b001000000 *
b000001101 +
#129
0#
#130
1#
b01100011 &
b01100110 )
b001000001 *
b000001110 +
#131
0#
b01100011 (
#132
1#
b01100010 &
b01100101 )
b001000010 *
b000001111 +
#133
0#
b01100010 (
#134
1#
b01101000 )
b001000011 *
b000010000 +
#135
0#
#136
1#
b01100001 &
b001000100 *
b000010001 +
#137
0#
b01100001 (
#138
1#
b01100010 &
b01101010 )
b001000101 *
b000010010 +
#139
0#
b01100010 (
#140
1#
b01100000 &
b01101000 )
b001000110 *
b000010011 +
#141
0#
b01100000 (
#142
1#
b01011111 &
b01101010 )
b001000111 *
b000010100 +
#143
0#
b01011111 (
#144
1#
b01100010 &
b01101011 )
b001001000 *
b000010101 +
#145
0#
b01100010 (
#146
1#
b01100000 &
b01101100 )
b001001001 *
b000010110 +
#147
0#
b01100000 (
#148
1#
b01100001 &
b001001010 *
b000010111 +
#149
0#
b01100001 (
#150
1#
b01100101 &
b01101101 )
b001001011 *
b000011000 +
#151
0#
b01100101 (
#152
1#
b01100011 &
b01101111 )
b001001100 *
b000011001 +
#153
0#
b01100011 (
#154
1#
b01101000 &
b01110011 )
b001001101 *
b000011010 +
#155
0#
b01101000 (
#156
1#
b01101011 &
b01110101 )
b001001110 *
b000011011 +
#157
0#
b01101011 (
#158
1#
b01101001 &
b001001111 *
b000011100 +
#159
0#
b01101001 (
#160
1#
b01101011 &
b01110100 )
b001010000 *
b000011101 +
#161
0#
b01101011 (
#162
1#
b01101101 &
b01110110 )
b001010001 *
b000011110 +
#163
0#
b01101101 (
#164
1#
b001010010 *
b000011111 +
#165
0#
#166
1#
b01101011 &
b01110101 )
b001010011 *
b000100000 +
#167
0#
b01101011 (
#168
1#
b01101100 &
b01110011 )
b001010100 *
b000100001 +
#169
0#
b01101100 (
#170
1#
b01101110 &
b01110101 )
b001010101 *
b000100010 +
#171
0#
b01101110 (
#172
1#
b01101101 &
b01110010 )
b001010110 *
b000100011 +
#173
0#
b01101101 (
#174
1#
b01110000 &
b01101111 )
b001010111 *
b000100100 +
#175
0#
b01110000 (
#176
1#
b01110100 &
b001011000 *
b000100101 +
#177
0#
b01110100 (
#178
1#
b01110000 )
b001011001 *
b000100110 +
#179
0#
#180
1#
b01110011 &
b01110001 )
b001011010 *
b000100111 +
#181
0#
b01110011 (
#182
1#
b01110101 &
b01110000 )
b001011011 *
b000101000 +
#183
0#
b01110101 (
#184
1#
b01110111 &
b01110110 )
b001011100 *
b000101001 +
#185
0#
b01110111 (
#186
1#
b01110001 )
b001011101 *
b000101010 +
#187
0#
#188
1#
b01111001 &
b01110101 )
b001011110 *
b000101011 +
#189
0#
b01111001 (
#190
1#
b01111100 &
b01110100 )
b001011111 *
b000101100 +
#191
0#
b01111100 (
#192
1#
b01110110 )
b001100000 *
b000101101 +
#193
0#
#194
1#
b01111011 &
b01110100 )
b001100001 *
b000101110 +
#195
0#
b01111011 (
#196
1#
b01111111 &
b01110101 )
b001100010 *
b000101111 +
#197
0#
b01111111 (
#198
1#
b01111100 &
b01110001 )
b001100011 *
b000110000 +
#199
0#
b01111100 (
#200
1#
b001100100 *
b000110001 +
#201
0#
#202
1#
b01111011 &
b01101111 )
b001100101 *
b000110010 +
#203
0#
b01111011 (
#204
1#
b001100110 *
b000110011 +
#205
0#
#206
1#
b01111010 &
b01101100 )
b001100111 *
b000110100 +
#207
0#
b01111010 (
#208
1#
b01110111 &
b01101001 )
b001101000 *
b000110101 +
#209
0#
b01110111 (
#210
1#
b01111011 &
b01101011 )
b001101001 *
b000110110 +
#211
0#
b01111011 (
#212
1#
b01100111 )
b001101010 *
b000110111 +
#213
0#
#214
1#
b01111010 &
b01101001 )
b001101011 *
b000111000 +
#215
0#
b01111010 (
#216
1#
b01111011 &
b01101000 )
b001101100 *
b000111001 +
#217
0#
b01111011 (
#218
1#
b01111001 &
b01100101 )
b001101101 *
b000111010 +
#219
0#
b01111001 (
#220
1#
b01111101 &
b001101110 *
b000111011 +
#221
0#
b01111101 (
#222
1#
b01111100 &
b01100111 )
b001101111 *
b000111100 +
#223
0#
b01111100 (
#224
1#
b01111111 &
b01101000 )
b001110000 *
b000111101 +
#225
0#
b01111111 (
#226
1#
b01111010 &
b001110001 *
b000111110 +
#227
0#
b01111010 (
#228
1#
b01111111 &
b01100101 )
b001110010 *
b000111111 +
#229
0#
b01111111 (
#230
1#
b01111011 &
b001110011 *
b001000000 +
#231
0#
b01111011 (
#232
1#
b01110110 &
b01100011 )
b001110100 *
b001000001 +
#233
0#
b01110110 (
#234
1#
b01110101 &
b01100010 )
b001110101 *
b001000010 +
#235
0#
b01110101 (
#236
1#
b001110110 *
b001000011 +
#237
0#
#238
1#
b01110010 &
b01100001 )
b001110111 *
b001000100 +
#239
0#
b01110010 (
#240
1#
b01101111 &
b01100010 )
b001111000 *
b001000101 +
#241
0#
b01101111 (
#242
1#
b01110000 &
b01100000 )
b001111001 *
b001000110 +
#243
0#
b01110000 (
#244
1#
b01101110 &
b01011111 )
b001111010 *
b001000111 +
#245
0#
b01101110 (
#246
1#
b01101100 &
b01100010 )
b001111011 *
b001001000 +
#247
0#
b01101100 (
#248
1#
b01101011 &
b01100000 )
b001111100 *
b001001001 +
#249
0#
b01101011 (
#250
1#
b01101101 &
b01100001 )
b001111101 *
b001001010 +
#251
0#
b01101101 (
#252
1#
b01101011 &
b01100101 )
b001111110 *
b001001011 +
#253
0#
b01101011 (
#254
1#
b01101010 &
b01100011 )
b001111111 *
b001001100 +
#255
0#
b01101010 (
#256
1#
b01101000 )
b010000000 *
b001001101 +
#257
0#
#258
1#
b01101011 )
b010000001 *
b001001110 +
#259
0#
#260
1#
b01101100 &
b01101001 )
b010000010 *
b001001111 +
#261
0#
b01101100 (
#262
1#
b01100111 &
b01101011 )
b010000011 *
b001010000 +
#263
0#
b01100111 (
#264
1#
b01101101 )
b010000100 *
b001010001 +
#265
0#
#266
1#
b01100101 &
b010000101 *
b001010010 +
#267
0#
b01100101 (
#268
1#
b01100110 &
b01101011 )
b010000110 *
b001010011 +
#269
0#
b01100110 (
#270
1#
b01100100 &
b01101100 )
b010000111 *
b001010100 +
#271
0#
b01100100 (
#272
1#
b01101110 )
b010001000 *
b001010101 +
#273
0#
#274
1#
b01100010 &
b01101101 )
b010001001 *
b001010110 +
#275
0#
b01100010 (
#276
1#
b01110000 )
b010001010 *
b001010111 +
#277
0#
#278
1#
b01100001 &
b01110100 )
b010001011 *
b001011000 +
#279
0#
b01100001 (
#280
1#
b01100000 &
b010001100 *
b001011001 +
#281
0#
b01100000 (
#282
1#
b01100011 &
b01110011 )
b010001101 *
b001011010 +
#283
0#
b01100011 (
#284
1#
b01110101 )
b010001110 *
b001011011 +
#285
0#
#286
1#
b01110111 )
b010001111 *
b001011100 +
#287
0#
#288
1#
b01100010 &
b010010000 *
b001011101 +
#289
0#
b01100010 (
#290
1#
b01100100 &
b01111001 )
b010010001 *
b001011110 +
#291
0#
b01100100 (
#292
1#
b01101001 &
b01111100 )
b010010010 *
b001011111 +
#293
0#
b01101001 (
#294
1#
b010010011 *
b001100000 +
#295
0#
#296
1#
b01111011 )
b010010100 *
b001100001 +
#297
0#
#298
1#
b01101100 &
b01111111 )
b010010101 *
b001100010 +
#299
0#
b01101100 (
#300
1#
b01101101 &
b01111100 )
b010010110 *
b001100011 +
#301
0#
b01101101 (
#302
1#
b010010111 *
b001100100 +
#303
0#
#304
1#
b01101110 &
b01111011 )
b010011000 *
b001100101 +
#305
0#
b01101110 (
#306
1#
b01101111 &
b010011001 *
b001100110 +
#307
0#
b01101111 (
#308
1#
b01101110 &
b01111010 )
b010011010 *
b001100111 +
#309
0#
b01101110 (
#310
1#
b01101010 &
b01110111 )
b010011011 *
b001101000 +
#311
0#
b01101010 (
#312
1#
b01111011 )
b010011100 *
b001101001 +
#313
0#
#314
1#
b01101011 &
b010011101 *
b001101010 +
#315
0#
b01101011 (
#316
1#
b01101001 &
b01111010 )
b010011110 *
b001101011 +
#317
0#
b01101001 (
#318
1#
b01101101 &
b01111011 )
b010011111 *
b001101100 +
#319
0#
b01101101 (
#320
1#
b01101100 &
b01111001 )
b010100000 *
b001101101 +
#321
0#
b01101100 (
#322
1#
b01101111 &
b01111101 )
b010100001 *
b001101110 +
#323
0#
b01101111 (
#324
1#
b01111100 )
b010100010 *
b001101111 +
#325
0#
#326
1#
b01110011 &
b01111111 )
b010100011 *
b001110000 +
#327
0#
b01110011 (
#328
1#
b01110010 &
b01111010 )
b010100100 *
b001110001 +
#329
0#
b01110010 (
#330
1#
b01110001 &
b01111111 )
b010100101 *
b001110010 +
#331
0#
b01110001 (
#332
1#
b01111011 )
b010100110 *
b001110011 +
#333
0#
#334
1#
b01110000 &
b01110110 )
b010100111 *
b001110100 +
#335
0#
b01110000 (
#336
1#
b01110101 )
b010101000 *
b001110101 +
#337
0#
#338
1#
b01101110 &
b010101001 *
b001110110 +
#339
0#
b01101110 (
#340
1#
b01101111 &
b01110010 )
b010101010 *
b001110111 +
#341
0#
b01101111 (
#342
1#
b01101111 )
b010101011 *
b001111000 +
#343
0#
#344
1#
b01101101 &
b01110000 )
b010101100 *
b001111001 +
#345
0#
b01101101 (
#346
1#
b01101110 &
b01101110 )
b010101101 *
b001111010 +
#347
0#
b01101110 (
#348
1#
b01101101 &
b01101100 )
b010101110 *
b001111011 +
#349
0#
b01101101 (
#350
1#
b01101110 &
b01101011 )
b010101111 *
b001111100 +
#351
0#
b01101110 (
#352
1#
b01101111 &
b01101101 )
b010110000 *
b001111101 +
#353
0#
b01101111 (
#354
1#
b01101101 &
b01101011 )
b010110001 *
b001111110 +
#355
0#
b01101101 (
#356
1#
b01101100 &
b01101010 )
b010110010 *
b001111111 +
#357
0#
b01101100 (
#358
1#
b01101101 &
b010110011 *
b010000000 +
#359
0#
b01101101 (
#360
1#
b01101111 &
b010110100 *
b010000001 +
#361
0#
b01101111 (
#362
1#
b01101110 &
b01101100 )
b010110101 *
b010000010 +
#363
0#
b01101110 (
#364
1#
b01101100 &
b01100111 )
b010110110 *
b010000011 +
#365
0#
b01101100 (
#366
1#
b01110000 &
b010110111 *
b010000100 +
#367
0#
b01110000 (
#368
1#
b01101111 &
b01100101 )
b010111000 *
b010000101 +
#369
0#
b01101111 (
#370
1#
b01100110 )
b010111001 *
b010000110 +
#371
0#
#372
1#
b01101001 &
b01100100 )
b010111010 *
b010000111 +
#373
0#
b01101001 (
#374
1#
b01101010 &
b010111011 *
b010001000 +
#375
0#
b01101010 (
#376
1#
b01100111 &
b01100010 )
b010111100 *
b010001001 +
#377
0#
b01100111 (
#378
1#
b01100110 &
b010111101 *
b010001010 +
#379
0#
b01100110 (
#380
1#
b01100101 &
b01100001 )
b010111110 *
b010001011 +
#381
0#
b01100101 (
#382
1#
b01100000 )
b010111111 *
b010001100 +
#383
0#
#384
1#
b01100100 &
b01100011 )
b011000000 *
b010001101 +
#385
0#
b01100100 (
#386
1#
b01100101 &
b011000001 *
b010001110 +
#387
0#
b01100101 (
#388
1#
b01101001 &
b011000010 *
b010001111 +
#389
0#
b01101001 (
#390
1#
b01101110 &
b01100010 )
b011000011 *
b010010000 +
#391
0#
b01101110 (
#392
1#
b01101100 &
b01100100 )
b011000100 *
b010010001 +
#393
0#
b01101100 (
#394
1#
b01101001 )
b011000101 *
b010010010 +
#395
0#
#396
1#
b01101000 &
b011000110 *
b010010011 +
#397
0#
b01101000 (
#398
1#
b01101100 &
b011000111 *
b010010100 +
#399
0#
b01101100 (
#400
1#
b01101011 &
b01101100 )
b011001000 *
b010010101 +
#401
0#
b01101011 (
#402
1#
b01101001 &
b01101101 )
b011001001 *
b010010110 +
#403
0#
b01101001 (
#404
1#
b01100110 &
b011001010 *
b010010111 +
#405
0#
b01100110 (
#406
1#
b01100010 &
b01101110 )
b011001011 *
b010011000 +
#407
0#
b01100010 (
#408
1#
b01100011 &
b01101111 )
b011001100 *
b010011001 +
#409
0#
b01100011 (
#410
1#
b01100010 &
b01101110 )
b011001101 *
b010011010 +
#411
0#
b01100010 (
#412
1#
b01100011 &
b01101010 )
b011001110 *
b010011011 +
#413
0#
b01100011 (
#414
1#
b01100101 &
b011001111 *
b010011100 +
#415
0#
b01100101 (
#416
1#
b01101000 &
b01101011 )
b011010000 *
b010011101 +
#417
0#
b01101000 (
#418
1#
b01100101 &
b01101001 )
b011010001 *
b010011110 +
#419
0#
b01100101 (
#420
1#
b01101000 &
b01101101 )
b011010010 *
b010011111 +
#421
0#
b01101000 (
#422
1#
b01101100 &
b01101100 )
b011010011 *
b010100000 +
#423
0#
b01101100 (
#424
1#
b01101011 &
b01101111 )
b011010100 *
b010100001 +
#425
0#
b01101011 (
#426
1#
b01101001 &
b011010101 *
b010100010 +
#427
0#
b01101001 (
#428
1#
b01101101 &
b01110011 )
b011010110 *
b010100011 +
#429
0#
b01101101 (
#430
1#
b01101111 &
b01110010 )
b011010111 *
b010100100 +
#431
0#
b01101111 (
#432
1#
b01110010 &
b01110001 )
b011011000 *
b010100101 +
#433
0#
b01110010 (
#434
1#
b01110001 &
b011011001 *
b010100110 +
#435
0#
b01110001 (
#436
1#
b01110000 )
b011011010 *
b010100111 +
#437
0#
#438
1#
b01110010 &
b011011011 *
b010101000 +
#439
0#
b01110010 (
#440
1#
b01101110 )
b011011100 *
b010101001 +
#441
0#
#442
1#
b01110100 &
b01101111 )
b011011101 *
b010101010 +
#443
0#
b01110100 (
#444
1#
b01110111 &
b011011110 *
b010101011 +
#445
0#
b01110111 (
#446
1#
b01110011 &
b01101101 )
b011011111 *
b010101100 +
#447
0#
b01110011 (
#448
1#
b01110110 &
b01101110 )
b011100000 *
b010101101 +
#449
0#
b01110110 (
#450
1#
b01110111 &
b01101101 )
b011100001 *
b010101110 +
#451
0#
b01110111 (
#452
1#
b01110101 &
b01101110 )
b011100010 *
b010101111 +
#453
0#
b01110101 (
#454
1#
b01110011 &
b01101111 )
b011100011 *
b010110000 +
#455
0#
b01110011 (
#456
1#
b01110110 &
b01101101 )
b011100100 *
b010110001 +
#457
0#
b01110110 (
#458
1#
b01110111 &
b01101100 )
b011100101 *
b010110010 +
#459
0#
b01110111 (
#460
1#
b01111010 &
b01101101 )
b011100110 *
b010110011 +
#461
0#
b01111010 (
#462
1#
b01111011 &
b01101111 )
b011100111 *
b010110100 +
#463
0#
b01111011 (
#464
1#
b01101110 )
b011101000 *
b010110101 +
#465
0#
#466
1#
b01111100 &
b01101100 )
b011101001 *
b010110110 +
#467
0#
b01111100 (
#468
1#
b01111011 &
b01110000 )
b011101010 *
b010110111 +
#469
0#
b01111011 (
#470
1#
b01110111 &
b01101111 )
b011101011 *
b010111000 +
#471
0#
b01110111 (
#472
1#
b01110110 &
b011101100 *
b010111001 +
#473
0#
b01110110 (
#474
1#
b01110111 &
b01101001 )
b011101101 *
b010111010 +
#475
0#
b01110111 (
#476
1#
b01111001 &
b01101010 )
b011101110 *
b010111011 +
#477
0#
b01111001 (
#478
1#
b01111000 &
b01100111 )
b011101111 *
b010111100 +
#479
0#
b01111000 (
#480
1#
b01100110 )
b011110000 *
b010111101 +
#481
0#
#482
1#
b01110111 &
b01100101 )
b011110001 *
b010111110 +
#483
0#
b01110111 (
#484
1#
b01110010 &
b011110010 *
b010111111 +
#485
0#
b01110010 (
#486
1#
b01110101 &
b01100100 )
b011110011 *
b011000000 +
#487
0#
b01110101 (
#488
1#
b01100101 )
b011110100 *
b011000001 +
#489
0#
#490
1#
b01111000 &
b01101001 )
b011110101 *
b011000010 +
#491
0#
b01111000 (
#492
1#
b01110110 &
b01101110 )
b011110110 *
b011000011 +
#493
0#
b01110110 (
#494
1#
b01110100 &
b01101100 )
b011110111 *
b011000100 +
#495
0#
b01110100 (
#496
1#
b01110011 &
b011111000 *
b011000101 +
#497
0#
b01110011 (
#498
1#
b01110001 &
b01101000 )
b011111001 *
b011000110 +
#499
0#
b01110001 (
#500
1#
b01101110 &
b01101100 )
b011111010 *
b011000111 +
#501
0#
b01101110 (
#502
1#
b01101100 &
b01101011 )
b011111011 *
b011001000 +
#503
0#
b01101100 (
#504
1#
b01101110 &
b01101001 )
b011111100 *
b011001001 +
#505
0#
b01101110 (
#506
1#
b01110000 &
b01100110 )
b011111101 *
b011001010 +
#507
0#
b01110000 (
#508
1#
b01110011 &
b01100010 )
b011111110 *
b011001011 +
#509
0#
b01110011 (
#510
1#
b01110010 &
b01100011 )
b011111111 *
b011001100 +
#511
0#
b01110010 (
#512
1#
b01110001 &
b01100010 )
b100000000 *
b011001101 +
#513
0#
b01110001 (
#514
1#
b01101110 &
b01100011 )
b100000001 *
b011001110 +
#515
0#
b01101110 (
#516
1#
b01101011 &
b01100101 )
b100000010 *
b011001111 +
#517
0#
b01101011 (
#518
1#
b01101101 &
b01101000 )
b100000011 *
b011010000 +
#519
0#
b01101101 (
#520
1#
b01101100 &
b01100101 )
b100000100 *
b011010001 +
#521
0#
b01101100 (
#522
1#
b01101000 &
b01101000 )
b100000101 *
b011010010 +
#523
0#
b01101000 (
#524
1#
b01101100 )
b100000110 *
b011010011 +
#525
0#
#526
1#
b01100101 &
b01101011 )
b100000111 *
b011010100 +
#527
0#
b01100101 (
#528
1#
b01100100 &
b01101001 )
b100001000 *
b011010101 +
#529
0#
b01100100 (
#530
1#
b01101101 )
b100001001 *
b011010110 +
#531
0#
#532
1#
b01100110 &
b01101111 )
b100001010 *
b011010111 +
#533
0#
b01100110 (
#534
1#
b01101010 &
b01110010 )
b100001011 *
b011011000 +
#535
0#
b01101010 (
#536
1#
b01101001 &
b01110001 )
b100001100 *
b011011001 +
#537
0#
b01101001 (
#538
1#
b01101000 &
b100001101 *
b011011010 +
#539
0#
b01101000 (
#540
1#
b01101010 &
b01110010 )
b100001110 *
b011011011 +
#541
0#
b01101010 (
#542
1#
b01101000 &
b100001111 *
b011011100 +
#543
0#
b01101000 (
#544
1#
b01101001 &
b01110100 )
b100010000 *
b011011101 +
#545
0#
b01101001 (
#546
1#
b01110111 )
b100010001 *
b011011110 +
#547
0#
#548
1#
b01101010 &
b01110011 )
b100010010 *
b011011111 +
#549
0#
b01101010 (
#550
1#
b01101001 &
b01110110 )
b100010011 *
b011100000 +
#551
0#
b01101001 (
#552
1#
b01110111 )
b100010100 *
b011100001 +
#553
0#
#554
1#
b01101010 &
b01110101 )
b100010101 *
b011100010 +
#555
0#
b01101010 (
#556
1#
b01101011 &
b01110011 )
b100010110 *
b011100011 +
#557
0#
b01101011 (
#558
1#
b01101110 &
b01110110 )
b100010111 *
b011100100 +
#559
0#
b01101110 (
#560
1#
b01101011 &
b01110111 )
b100011000 *
b011100101 +
#561
0#
b01101011 (
#562
1#
b01111010 )
b100011001 *
b011100110 +
#563
0#
#564
1#
b01111011 )
b100011010 *
b011100111 +
#565
0#
#566
1#
b01101111 &
b100011011 *
b011101000 +
#567
0#
b01101111 (
#568
1#
b01111100 )
b100011100 *
b011101001 +
#569
0#
#570
1#
b01111011 )
b100011101 *
b011101010 +
#571
0#
#572
1#
b01110111 )
b100011110 *
b011101011 +
#573
0#
#574
1#
b01101110 &
b01110110 )
b100011111 *
b011101100 +
#575
0#
b01101110 (
#576
1#
b01101111 &
b01110111 )
b100100000 *
b011101101 +
#577
0#
b01101111 (
#578
1#
b01110101 &
b01111001 )
b100100001 *
b011101110 +
#579
0#
b01110101 (
#580
1#
b01110001 &
b01111000 )
b100100010 *
b011101111 +
#581
0#
b01110001 (
#582
1#
b01110101 &
b100100011 *
b011110000 +
#583
0#
b01110101 (
#584
1#
b01110010 &
b01110111 )
b100100100 *
b011110001 +
#585
0#
b01110010 (
#586
1#
b01110101 &
b01110010 )
b100100101 *
b011110010 +
#587
0#
b01110101 (
#588
1#
b01110111 &
b01110101 )
b100100110 *
b011110011 +
#589
0#
b01110111 (
#590
1#
b01111001 &
b100100111 *
b011110100 +
#591
0#
b01111001 (
#592
1#
b01110111 &
b01111000 )
b100101000 *
b011110101 +
#593
0#
b01110111 (
#594
1#
b01111000 &
b01110110 )
b100101001 *
b011110110 +
#595
0#
b01111000 (
#596
1#
b01110111 &
b01110100 )
b100101010 *
b011110111 +
#597
0#
b01110111 (
#598
1#
b01111010 &
b01110011 )
b100101011 *
b011111000 +
#599
0#
b01111010 (
#600
1#
b01110110 &
b01110001 )
b100101100 *
b011111001 +
#601
0#
b01110110 (
#602
1#
b01111001 &
b01101110 )
b100101101 *
b011111010 +
#603
0#
b01111001 (
#604
1#
b01111100 &
b01101100 )
b100101110 *
b011111011 +
#605
0#
b01111100 (
#606
1#
b01111010 &
b01101110 )
b100101111 *
b011111100 +
#607
0#
b01111010 (
#608
1#
b01111100 &
b01110000 )
b100110000 *
b011111101 +
#609
0#
b01111100 (
#610
1#
b01111001 &
b01110011 )
b100110001 *
b011111110 +
#611
0#
b01111001 (
#612
1#
b01110010 )
b100110010 *
b011111111 +
#613
0#
#614
1#
b01111100 &
b01110001 )
b100110011 *
b100000000 +
#615
0#
b01111100 (
#616
1#
b01101110 )
b100110100 *
b100000001 +
#617
0#
#618
1#
b01111011 &
b01101011 )
b100110101 *
b100000010 +
#619
0#
b01111011 (
#620
1#
b01110111 &
b01101101 )
b100110110 *
b100000011 +
#621
0#
b01110111 (
#622
1#
b01111000 &
b01101100 )
b100110111 *
b100000100 +
#623
0#
b01111000 (
#624
1#
b01101000 )
b100111000 *
b100000101 +
#625
0#
#626
1#
b01111010 &
b100111001 *
b100000110 +
#627
0#
b01111010 (
