task2/rom.sv
module rom #(
    parameter ADDRESS_WIDTH = 8,
    parameter DATA_WIDTH = 8
)(
    input logic clk,
    input logic [ADDRESS_WIDTH-1:0] addr,
    output logic [DATA_WIDTH-1:0] dout
);

logic [DATA_WIDTH-1:0] rom_array [2**ADDRESS_WIDTH-1:0];

initial begin
    $display("Loading rom.");
    $readmemh("sinerom.mem", rom_array);
end;

always_ff @(posedge clk) begin
    //output is synchronous
    dout <= rom_array[addr];
end
endmodule

task1/counter.sv
module counter #(
    parameter WIDTH = 8
)(
    // interface signals
    input logic clk, //clock
    input logic rst, //reset
    input logic en, //enable signal
    input logic [WIDTH-1:0] incr, //increment value
    output logic signed [WIDTH-1:0] count //count output
);
// Original Counter Logic, Only Count Up

always_ff @ (posedge clk)
    if (rst) count <= {WIDTH{1'b0}};
    else count <= count + {{WIDTH-1{1'b0}},en};
endmodule

task1/sinegen.sv
module sinegen#(
    parameter A_WIDTH =8,
    parameter D_WIDTH =8
)(
    input logic clk,
    input logic rst,
    input logic en,
    input logic [D_WIDTH-1:0] incr,
    output logic [D_WIDTH-1:0] dout
);
    logic [A_WIDTH-1:0] address;

counter addrCounter(
    .clk (clk),
    .rst (rst),
    .en (en),
    .incr (incr),
    .count(address)
);

rom sineRom (
    .clk (clk),
    .addr (address),
    .dout (dout)
);
endmodule

task1/sinegen.vcd
$version Generated by VerilatedVcd $end
$timescale 1ps $end
 $scope module TOP $end
  $var wire 1 # clk $end
  $var wire 1 $ rst $end
  $var wire 1 % en $end
  $var wire 8 & incr [7:0] $end
  $var wire 8 ' dout [7:0] $end
  $scope module sinegen $end
   $var wire 32 ) A_WIDTH [31:0] $end
   $var wire 32 ) D_WIDTH [31:0] $end
   $var wire 1 # clk $end
   $var wire 1 $ rst $end
   $var wire 1 % en $end
   $var wire 8 & incr [7:0] $end
   $var wire 8 ' dout [7:0] $end
   $var wire 8 ( address [7:0] $end
   $scope module addrCounter $end
    $var wire 32 ) WIDTH [31:0] $end
    $var wire 1 # clk $end
    $var wire 1 $ rst $end
    $var wire 1 % en $end
    $var wire 8 & incr [7:0] $end
    $var wire 8 ( count [7:0] $end
   $upscope $end
   $scope module sineRom $end
    $var wire 32 ) ADDRESS_WIDTH [31:0] $end
    $var wire 32 ) DATA_WIDTH [31:0] $end
    $var wire 1 # clk $end
    $var wire 8 ( addr [7:0] $end
    $var wire 8 ' dout [7:0] $end
   $upscope $end
  $upscope $end
 $upscope $end
$enddefinitions $end


#0
1#
0$
1%
b00000001 &
b00000000 '
b00000000 (
b00000000000000000000000000001000 )
#1
#2
0#
b00110100 &
#3
#4
1#
b11111110 '
b00000001 (
#5
#6
0#
#7
#8
1#
b11111101 '
b00000010 (
#9
#10
0#
#11
#12
1#
b00000011 (
#13
#14
0#
#15
#16
1#
b00000100 (
#17
#18
0#
#19
#20
1#
b00000101 (
#21
#22
0#
#23
#24
1#
b00000110 (
#25
#26
0#
#27
#28
1#
b11111100 '
b00000111 (
#29
#30
0#
#31
#32
1#
b00001000 (
#33
#34
0#
#35
#36
1#
b11111011 '
b00001001 (
#37
#38
0#
#39
#40
1#
b11111010 '
b00001010 (
#41
#42
0#
#43
#44
1#
b00001011 (
#45
#46
0#
#47
#48
1#
b11111001 '
b00001100 (
#49
#50
0#
#51
#52
1#
b11111000 '
b00001101 (
#53
#54
0#
#55
#56
1#
b11110111 '
b00001110 (
#57
#58
0#
#59
#60
1#
b11110110 '
b00001111 (
#61
#62
0#
#63
#64
1#
b11110101 '
b00010000 (
#65
#66
0#
#67
#68
1#
b11110100 '
b00010001 (
#69
#70
0#
#71
#72
1#
b11110011 '
b00010010 (
#73
#74
0#
#75
#76
1#
b11110001 '
b00010011 (
#77
#78
0#
#79
#80
1#
b11110000 '
b00010100 (
#81
#82
0#
#83
#84
1#
b11101111 '
b00010101 (
#85
#86
0#
#87
#88
1#
b11101101 '
b00010110 (
#89
#90
0#
#91
#92
1#
b11101011 '
b00010111 (
#93
#94
0#
#95
#96
1#
b11101010 '
b00011000 (
#97
#98
0#
#99
#100
1#
b11101000 '
b00011001 (
#101
#102
0#
#103
#104
1#
b11100110 '
b00011010 (
#105
#106
0#
#107
#108
1#
b11100101 '
b00011011 (
#109
#110
0#
#111
#112
1#
b11100011 '
b00011100 (
#113
#114
0#
#115
#116
1#
b11100001 '
b00011101 (
#117
#118
0#
#119
#120
1#
b11011111 '
b00011110 (
#121
#122
0#
#123
#124
1#
b11011101 '
b00011111 (
#125
#126
0#
#127
#128
1#
b11011010 '
b00100000 (
#129
#130
0#
#131
#132
1#
b11011000 '
b00100001 (
#133
#134
0#
#135
#136
1#
b11010110 '
b00100010 (
#137
#138
0#
#139
#140
1#
b11010100 '
b00100011 (
#141
#142
0#
#143
#144
1#
b11010001 '
b00100100 (
#145
#146
0#
#147
#148
1#
b11001111 '
b00100101 (
#149
#150
0#
#151
#152
1#
b11001101 '
b00100110 (
#153
#154
0#
#155
#156
1#
b11001010 '
b00100111 (
#157
#158
0#
#159
#160
1#
b11001000 '
b00101000 (
#161
#162
0#
#163
#164
1#
b11000101 '
b00101001 (
#165
#166
0#
#167
#168
1#
b11000010 '
b00101010 (
#169
#170
0#
#171
#172
1#
b11000000 '
b00101011 (
#173
#174
0#
#175
#176
1#
b10111101 '
b00101100 (
#177
#178
0#
#179
#180
1#
b10111010 '
b00101101 (
#181
#182
0#
#183
#184
1#
b10111000 '
b00101110 (
#185
#186
0#
#187
#188
1#
b10110101 '
b00101111 (
#189
#190
0#
#191
#192
1#
b10110010 '
b00110000 (
#193
#194
0#
#195
#196
1#
b10101111 '
b00110001 (
#197
#198
0#
#199
#200
1#
b10101100 '
b00110010 (
#201
#202
0#
#203
#204
1#
b10101001 '
b00110011 (
#205
#206
0#
#207
#208
1#
b10100110 '
b00110100 (
#209
#210
0#
#211
#212
1#
b10100011 '
b00110101 (
#213
#214
0#
#215
#216
1#
b10100000 '
b00110110 (
#217
#218
0#
#219
#220
1#
b10011101 '
b00110111 (
#221
#222
0#
#223
#224
1#
b10011010 '
b00111000 (
#225
#226
0#
#227
#228
1#
b10010111 '
b00111001 (
#229
#230
0#
#231
#232
1#
b10010100 '
b00111010 (
#233
#234
0#
#235
#236
1#
b10010001 '
b00111011 (
#237
#238
0#
#239
#240
1#
b10001110 '
b00111100 (
#241
#242
0#
#243
#244
1#
b10001011 '
b00111101 (
#245
#246
0#
#247
#248
1#
b10001000 '
b00111110 (
#249
#250
0#
#251
#252
1#
b10000101 '
b00111111 (
#253
#254
0#
#255
#256
1#
b10000010 '
b01000000 (
#257
#258
0#
#259
#260
1#
b01111110 '
b01000001 (
#261
#262
0#
#263
#264
1#
b01111011 '
b01000010 (
#265
#266
0#
#267
#268
1#
b01111000 '
b01000011 (
#269
#270
0#
#271
#272
1#
b01110101 '
b01000100 (
#273
#274
0#
#275
#276
1#
b01110010 '
b01000101 (
#277
#278
0#
#279
#280
1#
b01101111 '
b01000110 (
#281
#282
0#
#283
#284
1#
b01101100 '
b01000111 (
#285
#286
0#
#287
#288
1#
b01101001 '
b01001000 (
#289
#290
0#
#291
#292
1#
b01100110 '
b01001001 (
#293
#294
0#
#295
#296
1#
b01100011 '
b01001010 (
#297
#298
0#
#299
#300
1#
b01100000 '
b01001011 (
#301
#302
0#
#303
#304
1#
b01011101 '
b01001100 (
#305
#306
0#
#307
#308
1#
b01011010 '
b01001101 (
#309
#310
0#
#311
#312
1#
b01010111 '
b01001110 (
#313
#314
0#
#315
#316
1#
b01010100 '
b01001111 (
#317
#318
0#
#319
#320
1#
b01010001 '
b01010000 (
#321
#322
0#
#323
#324
1#
b01001110 '
b01010001 (
#325
#326
0#
#327
#328
1#
b01001011 '
b01010010 (
#329
#330
0#
#331
#332
1#
b01001000 '
b01010011 (
#333
#334
0#
#335
#336
1#
b01000101 '
b01010100 (
#337
#338
0#
#339
#340
1#
b01000011 '
b01010101 (
#341
#342
0#
#343
#344
1#
b01000000 '
b01010110 (
#345
#346
0#
#347
#348
1#
b00111101 '
b01010111 (
#349
#350
0#
#351
#352
1#
b00111011 '
b01011000 (
#353
#354
0#
#355
#356
1#
b00111000 '
b01011001 (
#357
#358
0#
#359
#360
1#
b00110101 '
b01011010 (
#361
#362
0#
#363
#364
1#
b00110011 '
b01011011 (
#365
#366
0#
#367
#368
1#
b00110000 '
b01011100 (
#369
#370
0#
#371
#372
1#
b00101110 '
b01011101 (
#373
#374
0#
#375
#376
1#
b00101100 '
b01011110 (
#377
#378
0#
#379
#380
1#
b00101001 '
b01011111 (
#381
#382
0#
#383
#384
1#
b00100111 '
b01100000 (
#385
#386
0#
#387
#388
1#
b00100101 '
b01100001 (
#389
#390
0#
#391
#392
1#
b00100011 '
b01100010 (
#393
#394
0#
#395
#396
1#
b00100000 '
b01100011 (
#397
#398
0#
#399
#400
1#
b00011110 '
b01100100 (
#401
#402
0#
#403
#404
1#
b00011100 '
b01100101 (
#405
#406
0#
#407
#408
1#
b00011010 '
b01100110 (
#409
#410
0#
#411
#412
1#
b00011000 '
b01100111 (
#413
#414
0#
#415
#416
1#
b00010111 '
b01101000 (
#417
#418
0#
#419
#420
1#
b00010101 '
b01101001 (
#421
#422
0#
#423
#424
1#
b00010011 '
b01101010 (
#425
#426
0#
#427
#428
1#
b00010010 '
b01101011 (
#429
#430
0#
#431
#432
1#
b00010000 '
b01101100 (
#433
#434
0#
#435
#436
1#
b00001110 '
b01101101 (
#437
#438
0#
#439
#440
1#
b00001101 '
b01101110 (
#441
#442
0#
#443
#444
1#
b00001100 '
b01101111 (
#445
#446
0#
#447
#448
1#
b00001010 '
b01110000 (
#449
#450
0#
#451
#452
1#
b00001001 '
b01110001 (
#453
#454
0#
#455
#456
1#
b00001000 '
b01110010 (
#457
#458
0#
#459
#460
1#
b00000111 '
b01110011 (
#461
#462
0#
#463
#464
1#
b00000110 '
b01110100 (
#465
#466
0#
#467
#468
1#
b00000101 '
b01110101 (
#469
#470
0#
#471
#472
1#
b00000100 '
b01110110 (
#473
#474
0#
#475
#476
1#
b00000011 '
b01110111 (
#477
#478
0#
#479
#480
1#
b01111000 (
#481
#482
0#
#483
#484
1#
b00000010 '
b01111001 (
#485
#486
0#
#487
#488
1#
b00000001 '
b01111010 (
#489
#490
0#
#491
#492
1#
b01111011 (
#493
#494
0#
#495
#496
1#
b00000000 '
b01111100 (
#497
#498
0#
#499
#500
1#
b01111101 (
#501
#502
0#
#503
#504
1#
b01111110 (
#505
#506
0#
#507
#508
1#
b01111111 (
#509
#510
0#
#511
#512
1#
b10000000 (
#513
#514
0#
#515
#516
1#
b10000001 (
#517
#518
0#
#519
#520
1#
b10000010 (
#521
#522
0#
#523
#524
1#
b10000011 (
#525
#526
0#
#527
#528
1#
b10000100 (
#529
#530
0#
#531
#532
1#
b10000101 (
#533
#534
0#
#535
#536
1#
b10000110 (
#537
#538
0#
#539
#540
1#
b00000001 '
b10000111 (
#541
#542
0#
#543
#544
1#
b10001000 (
#545
#546
0#
#547
#548
1#
b00000010 '
b10001001 (
#549
#550
0#
#551
#552
1#
b00000011 '
b10001010 (
#553
#554
0#
#555
#556
1#
b10001011 (
#557
#558
0#
#559
#560
1#
b00000100 '
b10001100 (
#561
#562
0#
#563
#564
1#
b00000101 '
b10001101 (
#565
#566
0#
#567
#568
1#
b00000110 '
b10001110 (
#569
#570
0#
#571
#572
1#
b00000111 '
b10001111 (
#573
#574
0#
#575
#576
1#
b00001000 '
b10010000 (
#577
#578
0#
#579
#580
1#
b00001001 '
b10010001 (
#581
#582
0#
#583
#584
1#
b00001010 '
b10010010 (
#585
#586
0#
#587
#588
1#
b00001100 '
b10010011 (
#589
#590
0#
#591
#592
1#
b00001101 '
b10010100 (
#593
#594
0#
#595
#596
1#
b00001110 '
b10010101 (
#597
#598
0#
#599
#600
1#
b00010000 '
b10010110 (
#601
#602
0#
#603
#604
1#
b00010010 '
b10010111 (
#605
#606
0#
#607
#608
1#
b00010011 '
b10011000 (
#609
#610
0#
#611
#612
1#
b00010101 '
b10011001 (
#613
#614
0#
#615
#616
1#
b00010111 '
b10011010 (
#617
#618
0#
#619
#620
1#
b00011000 '
b10011011 (
#621
#622
0#
#623
#624
1#
b00011010 '
b10011100 (
#625
#626
0#
#627
#628
1#
b00011100 '
b10011101 (
#629
#630
0#
#631
#632
1#
b00011110 '
b10011110 (
#633
#634
0#
#635
#636
1#
b00100000 '
b10011111 (
#637
#638
0#
#639
#640
1#
b00100011 '
b10100000 (
#641
#642
0#
#643
#644
1#
b00100101 '
b10100001 (
#645
#646
0#
#647
#648
1#
b00100111 '
b10100010 (
#649
#650
0#
#651
#652
1#
b00101001 '
b10100011 (
#653
#654
0#
#655
#656
1#
b00101100 '
b10100100 (
#657
#658
0#
#659
#660
1#
b00101110 '
b10100101 (
#661
#662
0#
#663
#664
1#
b00110000 '
b10100110 (
#665
#666
0#
#667
#668
1#
b00110011 '
b10100111 (
#669
#670
0#
#671
#672
1#
b00110101 '
b10101000 (
#673
#674
0#
#675
#676
1#
b00111000 '
b10101001 (
#677
#678
0#
#679
#680
1#
b00111011 '
b10101010 (
#681
#682
0#
#683
#684
1#
b00111101 '
b10101011 (
#685
#686
0#
#687
#688
1#
b01000000 '
b10101100 (
#689
#690
0#
#691
#692
1#
b01000011 '
b10101101 (
#693
#694
0#
#695
#696
1#
b01000101 '
b10101110 (
#697
#698
0#
#699
#700
1#
b01001000 '
b10101111 (
#701
#702
0#
#703
#704
1#
b01001011 '
b10110000 (
#705
#706
0#
#707
#708
1#
b01001110 '
b10110001 (
#709
#710
0#
#711
#712
1#
b01010001 '
b10110010 (
#713
#714
0#
#715
#716
1#
b01010100 '
b10110011 (
#717
#718
0#
#719
#720
1#
b01010111 '
b10110100 (
#721
#722
0#
#723
#724
1#
b01011010 '
b10110101 (
#725
#726
0#
#727
#728
1#
b01011101 '
b10110110 (
#729
#730
0#
#731
#732
1#
b01100000 '
b10110111 (
#733
#734
0#
#735
#736
1#
b01100011 '
b10111000 (
#737
#738
0#
#739
#740
1#
b01100110 '
b10111001 (
#741
#742
0#
#743
#744
1#
b01101001 '
b10111010 (
#745
#746
0#
#747
#748
1#
b01101100 '
b10111011 (
#749
#750
0#
#751
#752
1#
b01101111 '
b10111100 (
#753
#754
0#
#755
#756
1#
b01110010 '
b10111101 (
#757
#758
0#
#759
#760
1#
b01110101 '
b10111110 (
#761
#762
0#
#763
#764
1#
b01111000 '
b10111111 (
#765
#766
0#
#767
#768
1#
b01111011 '
b11000000 (
#769
#770
0#
#771
#772
1#
b01111111 '
b11000001 (
#773
#774
0#
#775
#776
1#
b10000010 '
b11000010 (
#777
#778
0#
#779
#780
1#
b10000101 '
b11000011 (
#781
#782
0#
#783
#784
1#
b10001000 '
b11000100 (
#785
#786
0#
#787
#788
1#
b10001011 '
b11000101 (
#789
#790
0#
#791
#792
1#
b10001110 '
b11000110 (
#793
#794
0#
#795
#796
1#
b10010001 '
b11000111 (
#797
#798
0#
#799
#800
1#
b10010100 '
b11001000 (
#801
#802
0#
#803
#804
1#
b10010111 '
b11001001 (
#805
#806
0#
#807
#808
1#
b10011010 '
b11001010 (
#809
#810
0#
#811
#812
1#
b10011101 '
b11001011 (
#813
#814
0#
#815
#816
1#
b10100000 '
b11001100 (
#817
#818
0#
#819
#820
1#
b10100011 '
b11001101 (
#821
#822
0#
#823
#824
1#
b10100110 '
b11001110 (
#825
#826
0#
#827
#828
1#
b10101001 '
b11001111 (
#829
#830
0#
#831
#832
1#
b10101100 '
b11010000 (
#833
#834
0#
#835
#836
1#
b10101111 '
b11010001 (
#837
#838
0#
#839
#840
1#
b10110010 '
b11010010 (
#841
#842
0#
#843
#844
1#
b10110101 '
b11010011 (
#845
#846
0#
#847
#848
1#
b10111000 '
b11010100 (
#849
#850
0#
#851
#852
1#
b10111010 '
b11010101 (
#853
#854
0#
#855
#856
1#
b10111101 '
b11010110 (
#857
#858
0#
#859
#860
1#
b11000000 '
b11010111 (
#861
#862
0#
#863
#864
1#
b11000010 '
b11011000 (
#865
#866
0#
#867
#868
1#
b11000101 '
b11011001 (
#869
#870
0#
#871
#872
1#
b11001000 '
b11011010 (
#873
#874
0#
#875
#876
1#
b11001010 '
b11011011 (
#877
#878
0#
#879
#880
1#
b11001101 '
b11011100 (
#881
#882
0#
#883
#884
1#
b11001111 '
b11011101 (
#885
#886
0#
#887
#888
1#
b11010001 '
b11011110 (
#889
#890
0#
#891
#892
1#
b11010100 '
b11011111 (
#893
#894
0#
#895
#896
1#
b11010110 '
b11100000 (
#897
#898
0#
#899
#900
1#
b11011000 '
b11100001 (
#901
#902
0#
#903
#904
1#
b11011010 '
b11100010 (
#905
#906
0#
#907
#908
1#
b11011101 '
b11100011 (
#909
#910
0#
#911
#912
1#
b11011111 '
b11100100 (
#913
#914
0#
#915
#916
1#
b11100001 '
b11100101 (
#917
#918
0#
#919
#920
1#
b11100011 '
b11100110 (
#921
#922
0#
#923
#924
1#
b11100101 '
b11100111 (
#925
#926
0#
#927
#928
1#
b11100110 '
b11101000 (
#929
#930
0#
#931
#932
1#
b11101000 '
b11101001 (
#933
#934
0#
#935
#936
1#
b11101010 '
b11101010 (
#937
#938
0#
#939
#940
1#
b11101011 '
b11101011 (
#941
#942
0#
#943
#944
1#
b11101101 '
b11101100 (
#945
#946
0#
#947
#948
1#
b11101111 '
b11101101 (
#949
#950
0#
#951
#952
1#
b11110000 '
b11101110 (
#953
#954
0#
#955
#956
1#
b11110001 '
b11101111 (
#957
#958
0#
#959
#960
1#
b11110011 '
b11110000 (
#961
#962
0#
#963
#964
1#
b11110100 '
b11110001 (
#965
#966
0#
#967
#968
1#
b11110101 '
b11110010 (
#969
#970
0#
#971
#972
1#
b11110110 '
b11110011 (
#973
#974
0#
#975
#976
1#
b11110111 '
b11110100 (
#977
#978
0#
#979
#980
1#
b11111000 '
b11110101 (
#981
#982
0#
#983
#984
1#
b11111001 '
b11110110 (
#985
#986
0#
#987
#988
1#
b11111010 '
b11110111 (
#989
#990
0#
#991
#992
1#
b11111000 (
#993
#994
0#
#995
#996
1#
b11111011 '
b11111001 (
#997
#998
0#
#999
#1000
1#
b11111100 '
b11111010 (
#1001
#1002
0#
#1003
#1004
1#
b11111011 (
#1005
#1006
0#
#1007
#1008
1#
b11111101 '
b11111100 (
#1009
#1010
0#
#1011
#1012
1#
b11111101 (
#1013
#1014
0#
#1015
#1016
1#
b11111110 (
#1017
#1018
0#
#1019
#1020
1#
b11111111 (
#1021
#1022
0#
#1023
#1024
1#
b00000000 (
#1025
#1026
0#
#1027
#1028
1#
b11111110 '
b00000001 (
#1029
#1030
0#
#1031
#1032
1#
b11111101 '
b00000010 (
#1033
#1034
0#
#1035
#1036
1#
b00000011 (
#1037
#1038
0#
#1039
#1040
1#
b00000100 (
#1041
#1042
0#
#1043
#1044
1#
b00000101 (
#1045
#1046
0#
#1047
#1048
1#
b00000110 (
#1049
#1050
0#
#1051
#1052
1#
b11111100 '
b00000111 (
#1053
#1054
0#
#1055
#1056
1#
b00001000 (
#1057
#1058
0#
#1059
#1060
1#
b11111011 '
b00001001 (
#1061
#1062
0#
#1063
#1064
1#
b11111010 '
b00001010 (
#1065
#1066
0#
#1067
#1068
1#
b00001011 (
#1069
#1070
0#
#1071
#1072
1#
b11111001 '
b00001100 (
#1073
#1074
0#
#1075
#1076
1#
b11111000 '
b00001101 (
#1077
#1078
0#
#1079
#1080
1#
b11110111 '
b00001110 (
#1081
#1082
0#
#1083
#1084
1#
b11110110 '
b00001111 (
#1085
#1086
0#
#1087
#1088
1#
b11110101 '
b00010000 (
#1089
#1090
0#
#1091
#1092
1#
b11110100 '
b00010001 (
#1093
#1094
0#
#1095
#1096
1#
b11110011 '
b00010010 (
#1097
#1098
0#
#1099
#1100
1#
b11110001 '
b00010011 (
#1101
#1102
0#
#1103
#1104
1#
b11110000 '
b00010100 (
#1105
#1106
0#
#1107
#1108
1#
b11101111 '
b00010101 (
#1109
#1110
0#
#1111
#1112
1#
b11101101 '
b00010110 (
#1113
#1114
0#
#1115
#1116
1#
b11101011 '
b00010111 (
#1117
#1118
0#
#1119
#1120
1#
b11101010 '
b00011000 (
#1121
#1122
0#
#1123
#1124
1#
b11101000 '
b00011001 (
#1125
#1126
0#
#1127
#1128
1#
b11100110 '
b00011010 (
#1129
#1130
0#
#1131
#1132
1#
b11100101 '
b00011011 (
#1133
#1134
0#
#1135
#1136
1#
b11100011 '
b00011100 (
#1137
#1138
0#
#1139
#1140
1#
b11100001 '
b00011101 (
#1141
#1142
0#
#1143
#1144
1#
b11011111 '
b00011110 (
#1145
#1146
0#
#1147
#1148
1#
b11011101 '
b00011111 (
#1149
#1150
0#
#1151
#1152
1#
b11011010 '
b00100000 (
#1153
#1154
0#
#1155
#1156
1#
b11011000 '
b00100001 (
#1157
#1158
0#
#1159
#1160
1#
b11010110 '
b00100010 (
#1161
#1162
0#
#1163
#1164
1#
b11010100 '
b00100011 (
#1165
#1166
0#
#1167
#1168
1#
b11010001 '
b00100100 (
#1169
#1170
0#
#1171
#1172
1#
b11001111 '
b00100101 (
#1173
#1174
0#
#1175
#1176
1#
b11001101 '
b00100110 (
#1177
#1178
0#
#1179
#1180
1#
b11001010 '
b00100111 (
#1181
#1182
0#
#1183
#1184
1#
b11001000 '
b00101000 (
#1185
#1186
0#
#1187
#1188
1#
b11000101 '
b00101001 (
#1189
#1190
0#
#1191
#1192
1#
b11000010 '
b00101010 (
#1193
#1194
0#
#1195
#1196
1#
b11000000 '
b00101011 (
#1197
#1198
0#
#1199
#1200
1#
b10111101 '
b00101100 (
#1201
#1202
0#
#1203
#1204
1#
b10111010 '
b00101101 (
#1205
#1206
0#
#1207
#1208
1#
b10111000 '
b00101110 (
#1209
#1210
0#
#1211
#1212
1#
b10110101 '
b00101111 (
#1213
#1214
0#
#1215
#1216
1#
b10110010 '
b00110000 (
#1217
#1218
0#
#1219
#1220
1#
b10101111 '
b00110001 (
#1221
#1222
0#
#1223
#1224
1#
b10101100 '
b00110010 (
#1225
#1226
0#
#1227
#1228
1#
b10101001 '
b00110011 (
#1229
#1230
0#
#1231
#1232
1#
b10100110 '
b00110100 (
#1233
#1234
0#
#1235
#1236
1#
b10100011 '
b00110101 (
#1237
#1238
0#
#1239
#1240
1#
b10100000 '
b00110110 (
#1241
#1242
0#
#1243
#1244
1#
b10011101 '
b00110111 (
#1245
#1246
0#
#1247
#1248
1#
b10011010 '
b00111000 (
#1249
#1250
0#
#1251
#1252
1#
b10010111 '
b00111001 (
#1253
#1254
0#
#1255
#1256
1#
b10010100 '
b00111010 (
#1257
#1258
0#
#1259
#1260
1#
b10010001 '
b00111011 (
#1261
#1262
0#
#1263
#1264
1#
b10001110 '
b00111100 (
#1265
#1266
0#
#1267
#1268
1#
b10001011 '
b00111101 (
#1269
#1270
0#
#1271
#1272
1#
b10001000 '
b00111110 (
#1273
#1274
0#
#1275
#1276
1#
b10000101 '
b00111111 (
#1277
#1278
0#
#1279
#1280
1#
b10000010 '
b01000000 (
#1281
#1282
0#
#1283
#1284
1#
b01111110 '
b01000001 (
#1285
#1286
0#
#1287
#1288
1#
b01111011 '
b01000010 (
#1289
#1290
0#
#1291
#1292
1#
b01111000 '
b01000011 (
#1293
#1294
0#
#1295
#1296
1#
b01110101 '
b01000100 (
#1297
#1298
0#
#1299
#1300
1#
b01110010 '
b01000101 (
#1301
#1302
0#
#1303
#1304
1#
b01101111 '
b01000110 (
#1305
#1306
0#
#1307
#1308
1#
b01101100 '
b01000111 (
#1309
#1310
0#
#1311
#1312
1#
b01101001 '
b01001000 (
#1313
#1314
0#
#1315
#1316
1#
b01100110 '
b01001001 (
#1317
#1318
0#
#1319
#1320
1#
b01100011 '
b01001010 (
#1321
#1322
0#
#1323
#1324
1#
b01100000 '
b01001011 (
#1325
#1326
0#
#1327
#1328
1#
b01011101 '
b01001100 (
#1329
#1330
0#
#1331
#1332
1#
b01011010 '
b01001101 (
#1333
#1334
0#
#1335
#1336
1#
b01010111 '
b01001110 (
#1337
#1338
0#
#1339
#1340
1#
b01010100 '
b01001111 (
#1341
#1342
0#
#1343
#1344
1#
b01010001 '
b01010000 (
#1345
#1346
0#
#1347
#1348
1#
b01001110 '
b01010001 (
#1349
#1350
0#
#1351
#1352
1#
b01001011 '
b01010010 (
#1353
#1354
0#
#1355
#1356
1#
b01001000 '
b01010011 (
#1357
#1358
0#
#1359
#1360
1#
b01000101 '
b01010100 (
#1361
#1362
0#
#1363
#1364
1#
b01000011 '
b01010101 (
#1365
#1366
0#
#1367
#1368
1#
b01000000 '
b01010110 (
#1369
#1370
0#
#1371
#1372
1#
b00111101 '
b01010111 (
#1373
#1374
0#
#1375
#1376
1#
b00111011 '
b01011000 (
#1377
#1378
0#
#1379
#1380
1#
b00111000 '
b01011001 (
#1381
#1382
0#
#1383
#1384
1#
b00110101 '
b01011010 (
#1385
#1386
0#
#1387
#1388
1#
b00110011 '
b01011011 (
#1389
#1390
0#
#1391
#1392
1#
b00110000 '
b01011100 (
#1393
#1394
0#
#1395
#1396
1#
b00101110 '
b01011101 (
#1397
#1398
0#
#1399
#1400
1#
b00101100 '
b01011110 (
#1401
#1402
0#
#1403
#1404
1#
b00101001 '
b01011111 (
#1405
#1406
0#
#1407
#1408
1#
b00100111 '
b01100000 (
#1409
#1410
0#
#1411
#1412
1#
b00100101 '
b01100001 (
#1413
#1414
0#
#1415
#1416
1#
b00100011 '
b01100010 (
#1417
#1418
0#
#1419
#1420
1#
b00100000 '
b01100011 (
#1421
#1422
0#
#1423
#1424
1#
b00011110 '
b01100100 (
#1425
#1426
0#
#1427
#1428
1#
b00011100 '
b01100101 (
#1429
#1430
0#
#1431
#1432
1#
b00011010 '
b01100110 (
#1433
#1434
0#
#1435
#1436
1#
b00011000 '
b01100111 (
#1437
#1438
0#
#1439
#1440
1#
b00010111 '
b01101000 (
#1441
#1442
0#
#1443
#1444
1#
b00010101 '
b01101001 (
#1445
#1446
0#
#1447
#1448
1#
b00010011 '
b01101010 (
#1449
#1450
0#
#1451
#1452
1#
b00010010 '
b01101011 (
#1453
#1454
0#
#1455
#1456
1#
b00010000 '
b01101100 (
#1457
#1458
0#
#1459
#1460
1#
b00001110 '
b01101101 (
#1461
#1462
0#
#1463
#1464
1#
b00001101 '
b01101110 (
#1465
#1466
0#
#1467
#1468
1#
b00001100 '
b01101111 (
#1469
#1470
0#
#1471
#1472
1#
b00001010 '
b01110000 (
#1473
#1474
0#
#1475
#1476
1#
b00001001 '
b01110001 (
#1477
#1478
0#
#1479
#1480
1#
b00001000 '
b01110010 (
#1481
#1482
0#
#1483
#1484
1#
b00000111 '
b01110011 (
#1485
#1486
0#
#1487
#1488
1#
b00000110 '
b01110100 (
#1489
#1490
0#
#1491
#1492
1#
b00000101 '
b01110101 (
#1493
#1494
0#
#1495
#1496
1#
b00000100 '
b01110110 (
#1497
#1498
0#
#1499
#1500
1#
b00000011 '
b01110111 (
#1501
#1502
0#
#1503
#1504
1#
b01111000 (
#1505
#1506
0#
#1507
#1508
1#
b00000010 '
b01111001 (
#1509
#1510
0#
#1511
#1512
1#
b00000001 '
b01111010 (
#1513
#1514
0#
#1515
#1516
1#
b01111011 (
#1517
#1518
0#
#1519
#1520
1#
b00000000 '
b01111100 (
#1521
#1522
0#
#1523
#1524
1#
b01111101 (
#1525
#1526
0#
#1527
#1528
1#
b01111110 (
#1529
#1530
0#
#1531
#1532
1#
b01111111 (
#1533
#1534
0#
#1535
#1536
1#
b10000000 (
#1537
#1538
0#
#1539
#1540
1#
b10000001 (
#1541
#1542
0#
#1543
#1544
1#
b10000010 (
#1545
#1546
0#
#1547
#1548
1#
b10000011 (
#1549
#1550
0#
#1551
#1552
1#
b10000100 (
#1553
#1554
0#
#1555
#1556
1#
b10000101 (
#1557
#1558
0#
#1559
#1560
1#
b10000110 (
#1561
#1562
0#
#1563
#1564
1#
b00000001 '
b10000111 (
#1565
#1566
0#
#1567
#1568
1#
b10001000 (
#1569
#1570
0#
#1571
#1572
1#
b00000010 '
b10001001 (
#1573
#1574
0#
#1575
#1576
1#
b00000011 '
b10001010 (
#1577
#1578
0#
#1579
#1580
1#
b10001011 (
#1581
#1582
0#
#1583
#1584
1#
b00000100 '
b10001100 (
#1585
#1586
0#
#1587
#1588
1#
b00000101 '
b10001101 (
#1589
#1590
0#
#1591
#1592
1#
b00000110 '
b10001110 (
#1593
#1594
0#
#1595
#1596
1#
b00000111 '
b10001111 (
#1597
#1598
0#
#1599
#1600
1#
b00001000 '
b10010000 (
#1601
#1602
0#
#1603
#1604
1#
b00001001 '
b10010001 (
#1605
#1606
0#
#1607
#1608
1#
b00001010 '
b10010010 (
#1609
#1610
0#
#1611
#1612
1#
b00001100 '
b10010011 (
#1613
#1614
0#
#1615
#1616
1#
b00001101 '
b10010100 (
#1617
#1618
0#
#1619
#1620
1#
b00001110 '
b10010101 (
#1621
#1622
0#
#1623
#1624
1#
b00010000 '
b10010110 (
#1625
#1626
0#
#1627
#1628
1#
b00010010 '
b10010111 (
#1629
#1630
0#
#1631
#1632
1#
b00010011 '
b10011000 (
#1633
#1634
0#
#1635
#1636
1#
b00010101 '
b10011001 (
#1637
#1638
0#
#1639
#1640
1#
b00010111 '
b10011010 (
#1641
#1642
0#
#1643
#1644
1#
b00011000 '
b10011011 (
#1645
#1646
0#
#1647
#1648
1#
b00011010 '
b10011100 (
#1649
#1650
0#
#1651
#1652
1#
b00011100 '
b10011101 (
#1653
#1654
0#
#1655
#1656
1#
b00011110 '
b10011110 (
#1657
#1658
0#
#1659
#1660
1#
b00100000 '
b10011111 (
#1661
#1662
0#
#1663
#1664
1#
b00100011 '
b10100000 (
#1665
#1666
0#
#1667
#1668
1#
b00100101 '
b10100001 (
#1669
